litehash/__init__.py
litehash/_common.py
litehash/_equidistant.py
litehash/_fibonacci.py
litehash/_int_to_hexdigest.py
litehash-0.2.2.dist-info/LICENSE
litehash-0.2.2.dist-info/METADATA
litehash-0.2.2.dist-info/WHEEL
litehash-0.2.2.dist-info/top_level.txt
litehash-0.2.2.dist-info/RECORD
