Metadata-Version: 2.1
Name: litehash
Version: 0.2.2
Summary: Fast coarse hashes from files
Home-page: https://github.com/rtmigo/litehash_py
Author: Artëm IG
Author-email: ortemeo@gmail.com
License: MIT
Keywords: hash,file,fibonacci,crc32,md5,sha256
Platform: UNKNOWN
Classifier: Development Status :: 3 - Alpha
Classifier: Programming Language :: Python :: 3.7
Classifier: Programming Language :: Python :: 3.8
Classifier: Programming Language :: Python :: 3.9
Classifier: Programming Language :: Python :: 3.10
Classifier: Typing :: Typed
License-File: LICENSE
